adnd2e_combat_simulator/__init__.py
adnd2e_combat_simulator/combatants.example.yaml
adnd2e_combat_simulator-1.0.2.dist-info/DESCRIPTION.rst
adnd2e_combat_simulator-1.0.2.dist-info/METADATA
adnd2e_combat_simulator-1.0.2.dist-info/RECORD
adnd2e_combat_simulator-1.0.2.dist-info/WHEEL
adnd2e_combat_simulator-1.0.2.dist-info/entry_points.txt
adnd2e_combat_simulator-1.0.2.dist-info/metadata.json
adnd2e_combat_simulator-1.0.2.dist-info/top_level.txt
