Metadata-Version: 2.0
Name: adnd2e-combat-simulator
Version: 1.0.2
Summary: A tool to simulate combat in AD&D 2nd Edition
Home-page: https://github.com/gene1wood/adnd2e-combat-simulator
Author: Gene Wood
Author-email: gene_wood@cementhorizon.com
License: GPL-3.0
Keywords: ad&d d&d adnd dnd combat
Platform: UNKNOWN
Classifier: Development Status :: 3 - Alpha
Classifier: Intended Audience :: End Users/Desktop
Classifier: Topic :: Games/Entertainment :: Role-Playing
Classifier: License :: OSI Approved :: GNU General Public License v3 (GPLv3)
Classifier: Programming Language :: Python :: 2
Classifier: Programming Language :: Python :: 2.7
Requires-Dist: PyYAML
Requires-Dist: colorama
Requires-Dist: dice
